ProjetoLPOL/Main_CSV_to_JSON_Final.py
ProjetoLPOL/__init__.py
ProjetoLPOL-0.0.3.dist-info/LICENSE
ProjetoLPOL-0.0.3.dist-info/METADATA
ProjetoLPOL-0.0.3.dist-info/WHEEL
ProjetoLPOL-0.0.3.dist-info/top_level.txt
ProjetoLPOL-0.0.3.dist-info/RECORD
